Metadata-Version: 1.0
Name: dfsummary
Version: 0.4
Summary: A dataframe EDA helper package
Home-page: UNKNOWN
Author: Matthew Perkins
Author-email: UNKNOWN
License: UNKNOWN
Platform: UNKNOWN
